a_pandas_ex_fast_string/LICENSE
a_pandas_ex_fast_string/README.MD
a_pandas_ex_fast_string/__init__.py
a_pandas_ex_fast_string/requirements.txt
a_pandas_ex_fast_string/thirdparty.json
a_pandas_ex_fast_string-0.11.dist-info/LICENSE.rst
a_pandas_ex_fast_string-0.11.dist-info/METADATA
a_pandas_ex_fast_string-0.11.dist-info/WHEEL
a_pandas_ex_fast_string-0.11.dist-info/top_level.txt
a_pandas_ex_fast_string-0.11.dist-info/RECORD
